{
	"configurations" : 
	[
		{
			"directories" : 
			[
				{
					"build" : ".",
					"childIndexes" : 
					[
						1,
						4,
						5
					],
					"minimumCMakeVersion" : 
					{
						"string" : "3.5"
					},
					"projectIndex" : 0,
					"source" : "."
				},
				{
					"build" : "libs",
					"childIndexes" : 
					[
						2,
						3
					],
					"minimumCMakeVersion" : 
					{
						"string" : "3.5"
					},
					"parentIndex" : 0,
					"projectIndex" : 0,
					"source" : "libs"
				},
				{
					"build" : "libs/mnlibrary",
					"minimumCMakeVersion" : 
					{
						"string" : "3.5"
					},
					"parentIndex" : 1,
					"projectIndex" : 0,
					"source" : "libs/mnlibrary",
					"targetIndexes" : 
					[
						3
					]
				},
				{
					"build" : "libs/cqt",
					"minimumCMakeVersion" : 
					{
						"string" : "3.14"
					},
					"parentIndex" : 1,
					"projectIndex" : 1,
					"source" : "libs/cqt",
					"targetIndexes" : 
					[
						0,
						1
					]
				},
				{
					"build" : "src",
					"minimumCMakeVersion" : 
					{
						"string" : "3.14"
					},
					"parentIndex" : 0,
					"projectIndex" : 2,
					"source" : "src",
					"targetIndexes" : 
					[
						2
					]
				},
				{
					"build" : "tests",
					"childIndexes" : 
					[
						6
					],
					"minimumCMakeVersion" : 
					{
						"string" : "3.5"
					},
					"parentIndex" : 0,
					"projectIndex" : 0,
					"source" : "tests"
				},
				{
					"build" : "tests/mnlibrary",
					"minimumCMakeVersion" : 
					{
						"string" : "3.5"
					},
					"parentIndex" : 5,
					"projectIndex" : 3,
					"source" : "tests/mnlibrary",
					"targetIndexes" : 
					[
						4
					]
				}
			],
			"name" : "Debug",
			"projects" : 
			[
				{
					"childIndexes" : 
					[
						1,
						2,
						3
					],
					"directoryIndexes" : 
					[
						0,
						1,
						2,
						5
					],
					"name" : "zn_gestion",
					"targetIndexes" : 
					[
						3
					]
				},
				{
					"directoryIndexes" : 
					[
						3
					],
					"name" : "cqt",
					"parentIndex" : 0,
					"targetIndexes" : 
					[
						0,
						1
					]
				},
				{
					"directoryIndexes" : 
					[
						4
					],
					"name" : "gestion",
					"parentIndex" : 0,
					"targetIndexes" : 
					[
						2
					]
				},
				{
					"directoryIndexes" : 
					[
						6
					],
					"name" : "mnlibrary_test",
					"parentIndex" : 0,
					"targetIndexes" : 
					[
						4
					]
				}
			],
			"targets" : 
			[
				{
					"directoryIndex" : 3,
					"id" : "cqt::@7a5b1fcbfb9f1ab97050",
					"jsonFile" : "target-cqt-Debug-0b5b7c811e99cb0596c1.json",
					"name" : "cqt",
					"projectIndex" : 1
				},
				{
					"directoryIndex" : 3,
					"id" : "cqt_autogen::@7a5b1fcbfb9f1ab97050",
					"jsonFile" : "target-cqt_autogen-Debug-06a30049cba0a6d46c0c.json",
					"name" : "cqt_autogen",
					"projectIndex" : 1
				},
				{
					"directoryIndex" : 4,
					"id" : "gestion::@145eef247bfb46b6828c",
					"jsonFile" : "target-gestion-Debug-c03c452f32a4f6c8400a.json",
					"name" : "gestion",
					"projectIndex" : 2
				},
				{
					"directoryIndex" : 2,
					"id" : "mnlibrary::@32703b1e6f8f8bf34355",
					"jsonFile" : "target-mnlibrary-Debug-105f1fdc8ab37bf80416.json",
					"name" : "mnlibrary",
					"projectIndex" : 0
				},
				{
					"directoryIndex" : 6,
					"id" : "mnlibrary_test::@9546a73298042f905faf",
					"jsonFile" : "target-mnlibrary_test-Debug-ef32117b6f7045a474fa.json",
					"name" : "mnlibrary_test",
					"projectIndex" : 3
				}
			]
		}
	],
	"kind" : "codemodel",
	"paths" : 
	{
		"build" : "/Users/merhab/dev/emacs/zn_gestion/build",
		"source" : "/Users/merhab/dev/emacs/zn_gestion"
	},
	"version" : 
	{
		"major" : 2,
		"minor" : 1
	}
}
